{
 "actions": [],
 "allow_rename": 1,
 "creation": "2024-04-26 08:15:15.124114",
 "doctype": "DocType",
 "editable_grid": 1,
 "engine": "InnoDB",
 "field_order": [
  "channel_id"
 ],
 "fields": [
  {
   "fieldname": "channel_id",
   "fieldtype": "Link",
   "in_list_view": 1,
   "label": "Channel ID",
   "options": "Raven Channel",
   "reqd": 1
  }
 ],
 "index_web_pages_for_search": 1,
 "istable": 1,
 "links": [],
 "modified": "2024-04-26 08:16:02.277627",
 "modified_by": "Administrator",
 "module": "Raven",
 "name": "Raven Pinned Channels",
 "owner": "Administrator",
 "permissions": [],
 "sort_field": "modified",
 "sort_order": "DESC",
 "states": []
}